spybar/__init__.py
spybar/__main__.py
spybar/progress.py
spybar/utils.py
spybar-0.1.0.dist-info/entry_points.txt
spybar-0.1.0.dist-info/LICENSE
spybar-0.1.0.dist-info/WHEEL
spybar-0.1.0.dist-info/METADATA
spybar-0.1.0.dist-info/RECORD
