Metadata-Version: 2.1
Name: spybar
Version: 0.1.0
Summary: Adds progress bars to any file-reading tool (gzip, md5sum, etc)
License: WTFPL
Author: Rémy Sanchez
Author-email: remy.sanchez@hyperthese.net
Requires-Python: >=3.6,<4.0
Classifier: License :: Other/Proprietary License
Classifier: Programming Language :: Python :: 3
Classifier: Programming Language :: Python :: 3.6
Classifier: Programming Language :: Python :: 3.7
Classifier: Programming Language :: Python :: 3.8
Requires-Dist: psutil (>=5.6.7,<6.0.0)
Requires-Dist: tqdm (>=4.41.1,<5.0.0)
